FSPG/decoder_7seg.v
module decoder_7seg(code, decoded_output);

	input [1:0] code;
	output reg [6:0] decoded_output;

	always @(*) begin
		case (code)
			2'b00 : decoded_output = 7'b0000111;
			2'b01 : decoded_output = 7'b1110000;
			2'b10 : decoded_output = 7'b0011100;
			2'b11 : decoded_output = 7'b1100011;
			default : decoded_output = 7'b1111111;
		endcase
	end

endmodule

FSPG/two_bit_4to1muxV2.v
module two_bit_4to1muxV2 (s, u, v, w, x, m); // Starts a 2-bit 4-to-1 mux module written with always blocks.

    input [1:0] s; // Takes the 2-bit select value that picks one of four inputs.
    input [1:0] u, v, w, x; // Takes the four 2-bit input choices.
    output reg [1:0] m; // Stores the chosen 2-bit output.

    reg [1:0] t1, t2; // Holds the two middle 2-bit results before the final choice.

    always @(u, v, s[0]) begin // Updates the first middle result when u, v, or the low select bit changes.
        if (s[0] == 1'b1) // Checks if the low select bit asks for the second input in this pair.
            t1 = v; // Chooses v for the first pair when s[0] is 1.
        else // Handles the case where the low select bit is 0.
            t1 = u; // Chooses u for the first pair when s[0] is 0.
    end // Ends the first pair selection block.

    always @(w, x, s[0]) begin // Updates the second middle result when w, x, or the low select bit changes.
        if (s[0] == 1'b1) // Checks if the low select bit asks for the second input in this pair.
            t2 = x; // Chooses x for the second pair when s[0] is 1.
        else // Handles the case where the low select bit is 0.
            t2 = w; // Chooses w for the second pair when s[0] is 0.
    end // Ends the second pair selection block.

    always @(t1, t2, s[1]) begin // Updates the final output when the middle results or high select bit change.
        if (s[1] == 1'b1) // Checks if the high select bit asks for the second middle result.
            m = t2; // Sends the second middle result to the output.
        else // Handles the case where the high select bit is 0.
            m = t1; // Sends the first middle result to the output.
    end // Ends the final selection block.

endmodule // Ends the 2-bit 4-to-1 mux module.

part2/lab3_P2.v
module lab3_P2 (s,u,v,w,x,chosen_7segCode);
 
	input [1:0] s;
	input [1:0] u, v, w, x;
	output [6:0] chosen_7segCode;
	
	wire [1:0] temp;
	
	two_bit_4to1muxV2 part3(
		.s(s),
		.u(u),
		.v(v),
		.w(w),
		.x(x),
		.m(temp)
	);

	decoder_7seg part4(
		.code(temp),
		.decoded_output(chosen_7segCode)
	);

endmodule

part2/lab3_P2_TB.v
`timescale 1ns / 1ps
 
module lab3_P2_TB;
 
	reg [1:0] S, U, V, W, X;
	wire [6:0] output_7seg;

	lab3_P2 instantiate_p5 (
		.s(S),
		.u(U),
		.v(V),
		.w(W),
		.x(X),
		.chosen_7segCode(output_7seg)
	);
 	
	initial begin 
		$dumpfile("sim/lab3_p2.vcd");
		$dumpvars(0, lab3_P2_TB);

		// -----------------------------
		// Test set 1:
		// U = 00, V = 01, W = 10, X = 11
		// -----------------------------
		U = 2'b00; V = 2'b01; W = 2'b10; X = 2'b11;

		S = 2'b00; #20;   // m = 00, d = 0000111
		S = 2'b01; #20;   // m = 01, d = 1110000
		S = 2'b10; #20;   // m = 10, d = 0011100
		S = 2'b11; #20;   // m = 11, d = 1100011

		// -----------------------------
		// Test set 2:
		// U = 01, V = 10, W = 11, X = 00
		// -----------------------------
		U = 2'b01; V = 2'b10; W = 2'b11; X = 2'b00;

		S = 2'b00; #20;   // m = 01, d = 1110000
		S = 2'b01; #20;   // m = 10, d = 0011100
		S = 2'b10; #20;   // m = 11, d = 1100011
		S = 2'b11; #20;   // m = 00, d = 0000111

		$finish;
	end

endmodule

sim/lab3_p2.vcd
$date
	Mon Mar 23 13:50:19 2026
$end
$version
	Icarus Verilog
$end
$timescale
	1ps
$end
$scope module lab3_P2_TB $end
$var wire 7 ! output_7seg [6:0] $end
$var reg 2 " S [1:0] $end
$var reg 2 # U [1:0] $end
$var reg 2 $ V [1:0] $end
$var reg 2 % W [1:0] $end
$var reg 2 & X [1:0] $end
$scope module instantiate_p5 $end
$var wire 2 ' s [1:0] $end
$var wire 2 ( u [1:0] $end
$var wire 2 ) v [1:0] $end
$var wire 2 * w [1:0] $end
$var wire 2 + x [1:0] $end
$var wire 2 , temp [1:0] $end
$var wire 7 - chosen_7segCode [6:0] $end
$scope module part3 $end
$var wire 2 . s [1:0] $end
$var wire 2 / u [1:0] $end
$var wire 2 0 v [1:0] $end
$var wire 2 1 w [1:0] $end
$var wire 2 2 x [1:0] $end
$var reg 2 3 m [1:0] $end
$var reg 2 4 t1 [1:0] $end
$var reg 2 5 t2 [1:0] $end
$upscope $end
$scope module part4 $end
$var wire 2 6 code [1:0] $end
$var reg 7 7 decoded_output [6:0] $end
$upscope $end
$upscope $end
$upscope $end
$enddefinitions $end
$comment Show the parameter values. $end
$dumpall
$end
#0
$dumpvars
b111 7
b0 6
b10 5
b0 4
b0 3
b11 2
b10 1
b1 0
b0 /
b0 .
b111 -
b0 ,
b11 +
b10 *
b1 )
b0 (
b0 '
b11 &
b10 %
b1 $
b0 #
b0 "
b111 !
$end
#20000
b1110000 !
b1110000 -
b1110000 7
b1 ,
b1 3
b1 6
b1 4
b11 5
b1 "
b1 '
b1 .
#40000
b11100 !
b11100 -
b11100 7
b0 4
b10 5
b10 ,
b10 3
b10 6
b10 "
b10 '
b10 .
#60000
b1100011 !
b1100011 -
b1100011 7
b11 ,
b11 3
b11 6
b1 4
b11 5
b11 "
b11 '
b11 .
#80000
b1110000 !
b1110000 -
b1110000 7
b1 ,
b1 3
b1 6
b0 "
b0 '
b0 .
b0 &
b0 +
b0 2
b11 %
b11 *
b11 1
b10 $
b10 )
b10 0
b1 #
b1 (
b1 /
#100000
b11100 !
b11100 -
b11100 7
b10 ,
b10 3
b10 6
b10 4
b0 5
b1 "
b1 '
b1 .
#120000
b1100011 !
b1100011 -
b1100011 7
b1 4
b11 5
b11 ,
b11 3
b11 6
b10 "
b10 '
b10 .
#140000
b111 !
b111 -
b111 7
b0 ,
b0 3
b0 6
b10 4
b0 5
b11 "
b11 '
b11 .
