lab 2 code/common/one_bit_2to1mux.v
module one_bit_2to1mux (s,x,y,m); // Starts a 1-bit 2-to-1 mux module.
 
	input s, x, y; // Takes the select bit and the two possible input bits.
	output m; // Sends out the chosen bit.
	
	assign m = (~s & x) | (s & y); // Makes the output equal x when s is 0, or y when s is 1.
 
endmodule // Ends the 1-bit mux module.

lab 2 code/part1/four_bit_2to1mux.v
module four_bit_2to1mux (sel,a,b,chosen); // Starts a 4-bit mux built from four 1-bit muxes.
 
	input sel; // Takes the select bit used by all four bit positions.
	input[3:0] a, b; // Takes the two 4-bit values that can be chosen.
	output[3:0] chosen; // Sends out the final 4-bit chosen value.
	
    one_bit_2to1mux mux0(.s(sel), .x(a[0]), .y(b[0]), .m(chosen[0])); // Chooses the output bit for position 0.
    one_bit_2to1mux mux1(.s(sel), .x(a[1]), .y(b[1]), .m(chosen[1])); // Chooses the output bit for position 1.
    one_bit_2to1mux mux2(.s(sel), .x(a[2]), .y(b[2]), .m(chosen[2])); // Chooses the output bit for position 2.
    one_bit_2to1mux mux3(.s(sel), .x(a[3]), .y(b[3]), .m(chosen[3])); // Chooses the output bit for position 3.
 
endmodule // Ends the 4-bit mux module.

lab 2 code/part1/part1_TB.v
`timescale 1ns / 1ps // Sets the simulation time unit to 1 ns and the time precision to 1 ps.

module part1_TB; // Starts a testbench for the 4-bit 2-to-1 mux.

    reg [3:0] count; // Holds a counter that moves through the test cases.
    reg select; // Stores the select bit sent to the mux.
    reg [3:0] input1, input2; // Stores the two 4-bit input values used in each test.
    wire [3:0] output1; // Carries the mux output so the testbench can observe it.

    four_bit_2to1mux instantiate_mux4( // Creates the 4-bit mux being tested.
        .sel(select), // Connects the testbench select bit to the mux select input.
        .a(input1), // Connects the first test input bus to the mux.
        .b(input2), // Connects the second test input bus to the mux.
        .chosen(output1) // Connects the mux output to the observed test wire.
    ); // Finishes the mux connection.

    initial begin // Starts the one-time setup block for the simulation.
        $dumpfile("part1.vcd"); // Tells the simulator to save waveform data in part1.vcd.
        $dumpvars(0, part1_TB); // Tells the simulator which signals to include in the waveform file.

        count = 4'b0000; // Starts the test counter at zero.

        #500; // Lets the simulation run long enough to cover the planned test cases.
        $finish; // Stops the simulation after the test time is over.
    end // Ends the one-time setup block.

    always begin // Starts a repeating block that advances the test counter.
        #50; // Waits 50 ns between test cases.
        count = count + 4'b0001; // Moves to the next test case.
    end // Ends the repeating counter block.

    always @(count) begin // Updates the input values whenever the counter changes.
        case (count) // Chooses the test pattern for the current count value.
            4'b0000: begin input1 = 4'b0000; input2 = 4'b0001; select = 1'b0; end // Checks that input1 is chosen when select is 0.
            4'b0001: begin input1 = 4'b0010; input2 = 4'b0011; select = 1'b1; end // Checks that input2 is chosen when select is 1.
            4'b0010: begin input1 = 4'b0100; input2 = 4'b0111; select = 1'b0; end // Checks another case with input1 selected.
            4'b0011: begin input1 = 4'b1000; input2 = 4'b1111; select = 1'b1; end // Checks another case with input2 selected.
            default: begin input1 = 4'b0000; input2 = 4'b0000; select = 1'b0; end // Gives safe values after the listed cases.
        endcase // Ends the list of test patterns.
    end // Ends the block that applies test inputs.

endmodule // Ends the part 1 testbench.

lab 2 code/part1.vcd
$date
	Mon Mar 16 11:04:39 2026
$end
$version
	Icarus Verilog
$end
$timescale
	1ps
$end
$scope module part1_TB $end
$var wire 4 ! output1 [3:0] $end
$var reg 4 " count [3:0] $end
$var reg 4 # input1 [3:0] $end
$var reg 4 $ input2 [3:0] $end
$var reg 1 % select $end
$scope module instantiate_mux4 $end
$var wire 4 & a [3:0] $end
$var wire 4 ' b [3:0] $end
$var wire 1 % sel $end
$var wire 4 ( chosen [3:0] $end
$scope module mux0 $end
$var wire 1 ) m $end
$var wire 1 % s $end
$var wire 1 * x $end
$var wire 1 + y $end
$upscope $end
$scope module mux1 $end
$var wire 1 , m $end
$var wire 1 % s $end
$var wire 1 - x $end
$var wire 1 . y $end
$upscope $end
$scope module mux2 $end
$var wire 1 / m $end
$var wire 1 % s $end
$var wire 1 0 x $end
$var wire 1 1 y $end
$upscope $end
$scope module mux3 $end
$var wire 1 2 m $end
$var wire 1 % s $end
$var wire 1 3 x $end
$var wire 1 4 y $end
$upscope $end
$upscope $end
$upscope $end
$enddefinitions $end
$comment Show the parameter values. $end
$dumpall
$end
#0
$dumpvars
04
03
02
01
00
0/
0.
0-
0,
1+
0*
0)
b0 (
b1 '
b0 &
0%
b1 $
b0 #
b0 "
b0 !
$end
#50000
1)
b11 !
b11 (
1,
1.
1-
1%
b11 $
b11 '
b10 #
b10 &
b1 "
#100000
1/
0)
b100 !
b100 (
0,
11
0-
10
0%
b111 $
b111 '
b100 #
b100 &
b10 "
#150000
1)
1,
b1111 !
b1111 (
12
14
00
13
1%
b1111 $
b1111 '
b1000 #
b1000 &
b11 "
#200000
0)
0,
0/
b0 !
b0 (
02
0+
0.
01
04
03
0%
b0 $
b0 '
b0 #
b0 &
b100 "
#250000
b101 "
#300000
b110 "
#350000
b111 "
#400000
b1000 "
#450000
b1001 "
#500000
b1010 "
