lab 2 code/common/one_bit_2to1mux.v
module one_bit_2to1mux (s,x,y,m); // Starts a 1-bit 2-to-1 mux module.
 
	input s, x, y; // Takes the select bit and the two possible input bits.
	output m; // Sends out the chosen bit.
	
	assign m = (~s & x) | (s & y); // Makes the output equal x when s is 0, or y when s is 1.
 
endmodule // Ends the 1-bit mux module.

lab 2 code/part2/one_bit_4to1mux.v
module one_bit_4to1mux (s, u, v, w, x, m); // Starts a 1-bit 4-to-1 mux built from three 2-to-1 muxes.

    input [1:0] s; // Takes the 2-bit select value that picks one of four inputs.
    input u, v, w, x; // Takes the four 1-bit input choices.
    output m; // Sends out the chosen bit.

    wire t1, t2; // Holds the two middle results before the final choice.

    one_bit_2to1mux mux1(.s(s[0]), .x(u), .y(v), .m(t1)); // Uses the low select bit to choose between u and v.
    one_bit_2to1mux mux2(.s(s[0]), .x(w), .y(x), .m(t2)); // Uses the low select bit to choose between w and x.
    one_bit_2to1mux mux3(.s(s[1]), .x(t1), .y(t2), .m(m)); // Uses the high select bit to choose the final output.

endmodule // Ends the 1-bit 4-to-1 mux module.

lab 2 code/part2/part2_TB.v
`timescale 1ns / 1ps // Sets the simulation time unit to 1 ns and the time precision to 1 ps.
 
module part2_TB; // Starts a testbench for the 1-bit 4-to-1 mux.
 
	// This line starts a short note block about the testbench setup.
	// This line says the mux under test is created below.
	// This line says the testbench drives the inputs and checks the output.
 
	reg [3:0] count; // Holds a counter that steps through the test patterns.
	reg [1:0] select; // Stores the 2-bit select value for the mux.
	reg  input1, input2, input3, input4; // Stores the four input bits used in each test.
	wire output1; // Carries the mux output so the testbench can observe it.
	
	one_bit_4to1mux instantiate_mux4(.s(select),.u(input1),.v(input2),.w(input3),.x(input4),.m(output1)); // Creates the mux being tested and connects the test signals.
 	
	initial begin  // Starts the setup block that runs once at time 0.
	    $dumpfile("part2.vcd");
        $dumpvars(0, part2_TB);

		count = 4'b0000; // Starts the test counter at zero.

        #1000;
        $finish;
	end // Ends the one-time setup block.
	
	always begin // Starts a repeating block that advances the test counter.
		#50 // Waits 50 ns before moving to the next test case.
		count=count+4'b0001; // Increases the counter to trigger the next input pattern.
	end // Ends the repeating counter block.
	
	always @(count) begin // Updates the input values whenever the counter changes.
		case (count) // Chooses the test pattern for the current count value.
		4'b0000 : begin input1 = 1'b1; input2 = 1'b0; input3 = 1'b0; input4 = 1'b0; select = 2'b00; end // Checks that select 00 picks the first input.
		4'b0001 : begin input1 = 1'b1; input2 = 1'b0; input3 = 1'b0; input4 = 1'b0; select = 2'b01; end // Checks that select 01 moves away from the first input.
		4'b0010 : begin input1 = 1'b1; input2 = 1'b0; input3 = 1'b0; input4 = 1'b0; select = 2'b10; end // Checks that select 10 does not pick the first input.
		4'b0011 : begin input1 = 1'b1; input2 = 1'b0; input3 = 1'b0; input4 = 1'b0; select = 2'b11; end // Checks that select 11 does not pick the first input.
		4'b0100 : begin input1 = 1'b0; input2 = 1'b1; input3 = 1'b0; input4 = 1'b0; select = 2'b00; end // Checks that select 00 does not pick the second input.
		4'b0101 : begin input1 = 1'b0; input2 = 1'b1; input3 = 1'b0; input4 = 1'b0; select = 2'b01; end // Checks that select 01 picks the second input.
		4'b0110 : begin input1 = 1'b0; input2 = 1'b1; input3 = 1'b0; input4 = 1'b0; select = 2'b10; end // Checks that select 10 does not pick the second input.
		4'b0111 : begin input1 = 1'b0; input2 = 1'b1; input3 = 1'b0; input4 = 1'b0; select = 2'b11; end // Checks that select 11 does not pick the second input.
		default : begin input1 = 1'b0; input2 = 1'b0; input3 = 1'b0; input4 = 1'b0; select = 2'b00; end // Gives safe values after the listed cases.
	endcase // Ends the list of test patterns.
	end // Ends the block that applies test inputs.

 
endmodule // Ends the part 2 testbench.

lab 2 code/part2.vcd
$date
	Mon Mar 16 11:04:55 2026
$end
$version
	Icarus Verilog
$end
$timescale
	1ps
$end
$scope module part2_TB $end
$var wire 1 ! output1 $end
$var reg 4 " count [3:0] $end
$var reg 1 # input1 $end
$var reg 1 $ input2 $end
$var reg 1 % input3 $end
$var reg 1 & input4 $end
$var reg 2 ' select [1:0] $end
$scope module instantiate_mux4 $end
$var wire 2 ( s [1:0] $end
$var wire 1 # u $end
$var wire 1 $ v $end
$var wire 1 % w $end
$var wire 1 & x $end
$var wire 1 ) t2 $end
$var wire 1 * t1 $end
$var wire 1 ! m $end
$scope module mux1 $end
$var wire 1 * m $end
$var wire 1 + s $end
$var wire 1 # x $end
$var wire 1 $ y $end
$upscope $end
$scope module mux2 $end
$var wire 1 ) m $end
$var wire 1 , s $end
$var wire 1 % x $end
$var wire 1 & y $end
$upscope $end
$scope module mux3 $end
$var wire 1 ! m $end
$var wire 1 - s $end
$var wire 1 * x $end
$var wire 1 ) y $end
$upscope $end
$upscope $end
$upscope $end
$enddefinitions $end
$comment Show the parameter values. $end
$dumpall
$end
#0
$dumpvars
0-
0,
0+
1*
0)
b0 (
b0 '
0&
0%
0$
1#
b0 "
1!
$end
#50000
0!
0*
1+
1,
b1 '
b1 (
b1 "
#100000
1*
0+
0,
1-
b10 '
b10 (
b10 "
#150000
0*
1+
1,
b11 '
b11 (
b11 "
#200000
0!
0*
0+
0,
0-
b0 '
b0 (
1$
0#
b100 "
#250000
1!
1*
1+
1,
b1 '
b1 (
b101 "
#300000
0!
0*
0+
0,
1-
b10 '
b10 (
b110 "
#350000
1*
1+
1,
b11 '
b11 (
b111 "
#400000
0*
0+
0,
0-
b0 '
b0 (
0$
b1000 "
#450000
b1001 "
#500000
b1010 "
#550000
b1011 "
#600000
b1100 "
#650000
b1101 "
#700000
b1110 "
#750000
b1111 "
#800000
1!
1*
1#
b0 "
#850000
0!
0*
1+
1,
b1 '
b1 (
b1 "
#900000
1*
0+
0,
1-
b10 '
b10 (
b10 "
#950000
0*
1+
1,
b11 '
b11 (
b11 "
#1000000
0!
0*
0+
0,
0-
b0 '
b0 (
1$
0#
b100 "
